{
  "field_vocabs": {
    "pos": {
      "<PAD>": 0,
      "<UNK>": 1,
      "<CLS>": 2,
      "<MASK>": 3,
      "pron": 4,
      "prt": 5,
      "adv": 6,
      "v": 7,
      "auxv": 8,
      "n": 9,
      "auxs": 10,
      "suff": 11,
      "pref": 12,
      "int": 13,
      "adj": 14,
      "at": 15,
      "shp": 16,
      "space": 17,
      "conj": 18,
      "sym": 19
    },
    "pos_detail1": {
      "<PAD>": 0,
      "<UNK>": 1,
      "<CLS>": 2,
      "<MASK>": 3,
      "case_particle": 4,
      "non_self_reliant": 5,
      "common_noun": 6,
      "general": 7,
      "conjunctive_particle": 8,
      "sentence_final_particle": 9,
      "period": 10,
      "adverbial_particle": 11,
      "binding_particle": 12,
      "numeral": 13,
      "noun_like": 14,
      "comma": 15,
      "bracket_open": 16,
      "bracket_close": 17,
      "auxiliary_verb_stem": 18,
      "pre_noun_particle": 19,
      "proper_noun": 20,
      "ascii_art": 21,
      "adjectival": 22,
      "shape_word_like": 23,
      "verb_like": 24,
      "filler": 25,
      "tari": 26,
      "character": 27
    },
    "pos_detail2": {
      "<PAD>": 0,
      "<UNK>": 1,
      "<CLS>": 2,
      "<MASK>": 3,
      "suru-possible": 4,
      "adverb-possible": 5,
      "counter-possible": 6,
      "counter": 7,
      "pos2-unk1": 8,
      "pos2-unk2": 9,
      "person-name": 10,
      "place-name": 11,
      "kaomoji": 12
    },
    "conjugated_type": {
      "<PAD>": 0,
      "<UNK>": 1,
      "<CLS>": 2,
      "<MASK>": 3,
      "sa-irregular": 4,
      "auxv-ta": 5,
      "godan-ta": 6,
      "ka-irregular": 7,
      "i-ichidan-ma": 8,
      "auxv-masu": 9,
      "godan-ra": 10,
      "auxv-nai": 11,
      "auxv-nu": 12,
      "e-ichidan-ta": 13,
      "auxv-desu": 14,
      "godan-waa": 15,
      "adjective": 16,
      "auxv-da": 17,
      "i-ichidan-a": 18,
      "godan-ga": 19,
      "e-ichidan-ma": 20,
      "e-ichidan-ra": 21,
      "auxv-tai": 22,
      "i-ichidan-ka": 23,
      "e-ichidan-a": 24,
      "godan-ka": 25,
      "godan-ma": 26,
      "auxv-reru": 27,
      "e-ichidan-ka": 28,
      "godan-sa": 29,
      "e-ichidan-sa": 30,
      "i-ichidan-ga": 31,
      "e-ichidan-na": 32,
      "e-ichidan-ga": 33,
      "e-ichidan-da": 34,
      "e-ichidan-ba": 35,
      "godan-ba": 36,
      "i-ichidan-ba": 37,
      "godan-na": 38,
      "e-ichidan-ha": 39,
      "auxv-beshi": 40,
      "i-ichidan-za": 41,
      "i-ichidan-ta": 42,
      "classical-sa-irregular": 43,
      "auxv-rashii": 44,
      "i-ichidan-ra": 45,
      "i-ichidan-na": 46,
      "auxv-tari": 47,
      "auxv-nari-assertive": 48,
      "auxv-ki": 49,
      "auxv-nanda": 50,
      "classical-adjective-ku": 51,
      "yodan-ka": 52,
      "auxv-ri": 53,
      "yodan-ha": 54,
      "classical-irregular-ra": 55,
      "auxv-mai": 56,
      "auxv-mu": 57,
      "auxv-gotoshi": 58,
      "i-ichidan-ha": 59,
      "auxv-ja": 60,
      "auxv-zu": 61,
      "nidan-ra": 62,
      "auxv-ya": 63,
      "classical-adj-shiku": 64,
      "e-ichidan-za": 65,
      "yodan-ra": 66,
      "nidan-ma": 67,
      "auxv-zamasu": 68,
      "yodan-ma": 69,
      "upper-nidan-ba": 70,
      "upper-nidan-da": 71,
      "auxv-tari-perfective": 72,
      "auxv-ji": 73,
      "auxv-nu-classical": 74,
      "yodan-ta": 75,
      "yodan-sa": 76,
      "nidan-ka": 77,
      "auxv-keri": 78,
      "lower-nidan-sa": 79,
      "nidan-na": 80,
      "nidan-a": 81,
      "nidan-da": 82,
      "nidan-ga": 83,
      "auxv-ramu": 84,
      "auxv-hen": 85,
      "upper-nidan-ta": 86,
      "lower-nidan-ha": 87,
      "auxv-maji": 88,
      "auxv-rashi": 89
    },
    "conjugated_form": {
      "<PAD>": 0,
      "<UNK>": 1,
      "<CLS>": 2,
      "<MASK>": 3,
      "conjunctive": 4,
      "attributive": 5,
      "conjunctive-geminate": 6,
      "terminal": 7,
      "volitional-presumptive": 8,
      "imperfective": 9,
      "conditional": 10,
      "terminal-nasal": 11,
      "conjunctive-ni": 12,
      "conjunctive-nasal": 13,
      "conjunctive-i-sound": 14,
      "stem": 15,
      "imperative": 16,
      "conjunctive-fused": 17,
      "imperfective-sa": 18,
      "imperfective-se": 19,
      "attributive-nasal": 20,
      "attributive-auxiliary": 21,
      "stem-sa": 22,
      "attributive-abbreviated": 23,
      "realis": 24,
      "conditional-fused": 25,
      "terminal-fused": 26,
      "imperfective-auxiliary": 27,
      "imperfective-nasal": 28,
      "terminal-geminate": 29,
      "conjunctive-u-sound": 30,
      "terminal-u-sound": 31,
      "conjunctive-abbreviated": 32,
      "conjunctive-auxiliary": 33,
      "ku-form": 34
    },
    "lemma": {
      "<PAD>": 0,
      "<UNK>": 1,
      "<CLS>": 2,
      "<MASK>": 3,
      "だ": 4,
      "する": 5,
      "いる": 6,
      "ます": 7,
      "ない": 8,
      "?": 9,
      "なる": 10,
      "ぬ": 11,
      "ある": 12,
      "れる": 13,
      "行く": 14,
      "です": 15,
      "言う": 16,
      "思う": 17,
      "できる": 18,
      "知る": 19,
      "見る": 20,
      "た": 21,
      "くれる": 22,
      "くる": 23,
      "くださる": 24,
      "なさる": 25,
      "つく": 26,
      "やる": 27,
      "られる": 28,
      "持つ": 29,
      "来る": 30,
      "せる": 31,
      "!": 32,
      "1": 33,
      "べし": 34,
      "しまう": 35,
      "会う": 36,
      "聞く": 37,
      "てる": 38,
      "2": 39,
      "いける": 40,
      "食べる": 41,
      "話す": 42,
      "3": 43,
      "下さる": 44,
      "わかる": 45,
      "買う": 46,
      "出る": 47,
      "入る": 48,
      "いく": 49,
      "とる": 50,
      "住む": 51,
      "読む": 52,
      "書く": 53,
      "待つ": 54,
      "おく": 55,
      "みる": 56,
      "教える": 57,
      "たい": 58,
      "10": 59,
      "使う": 60,
      "考える": 61,
      "いう": 62,
      "分かる": 63,
      "よい": 64,
      "もらう": 65,
      "よる": 66,
      "飲む": 67,
      "早い": 68,
      "かかる": 69,
      "忘れる": 70,
      "かける": 71,
      "帰る": 72,
      "いただける": 73,
      "5": 74,
      "働く": 75,
      "始める": 76,
      "願う": 77,
      "見える": 78,
      "しれる": 79,
      "降る": 80,
      "出す": 81,
      "歩く": 82,
      "取る": 83,
      "入れる": 84,
      "つける": 85,
      "信ずる": 86,
      "作る": 87,
      "乗る": 88,
      "遅れる": 89,
      "あげる": 90,
      "死ぬ": 91,
      "寝る": 92,
      "出来る": 93,
      "6": 94,
      "すむ": 95,
      "受ける": 96,
      "起こる": 97,
      "着く": 98,
      "終わる": 99,
      "起きる": 100,
      "立つ": 101,
      "座る": 102,
      "すぎる": 103,
      "やめる": 104,
      "うまい": 105,
      "疲れる": 106,
      "呼ぶ": 107,
      "手伝う": 108,
      "走る": 109,
      "良い": 110,
      "戻る": 111,
      "4": 112,
      "もらえる": 113,
      "行う": 114,
      "送る": 115,
      "ござる": 116,
      "見つける": 117,
      "覚える": 118,
      "生きる": 119,
      "与える": 120,
      "探す": 121,
      "急ぐ": 122,
      "出かける": 123,
      "おる": 124,
      "続ける": 125,
      "得る": 126,
      "着る": 127,
      "生まれる": 128,
      "貸す": 129,
      "怒る": 130,
      "対する": 131,
      "驚く": 132,
      "いたす": 133,
      "笑う": 134,
      "泣く": 135,
      "いただく": 136,
      "終える": 137,
      "7": 138,
      "見せる": 139,
      "開く": 140,
      "開ける": 141,
      "決める": 142,
      "喜ぶ": 143,
      "置く": 144,
      "助ける": 145,
      "求める": 146,
      "間違う": 147,
      "愛する": 148,
      "借りる": 149,
      "困る": 150,
      "選ぶ": 151,
      "悪い": 152,
      "感ずる": 153,
      "高い": 154,
      "聞こえる": 155,
      "8": 156,
      "眠る": 157,
      "立てる": 158,
      "遊ぶ": 159,
      "似る": 160,
      "泳ぐ": 161,
      "話せる": 162,
      "30": 163,
      "楽しい": 164,
      "過ごす": 165,
      "頼む": 166,
      "落ちる": 167,
      "大きい": 168,
      "払う": 169,
      "ちゃう": 170,
      "速い": 171,
      "答える": 172,
      "向かう": 173,
      "楽しむ": 174,
      "2人": 175,
      "変わる": 176,
      "もつ": 177,
      "20": 178,
      "合う": 179,
      "休む": 180,
      "ひどい": 181,
      "忙しい": 182,
      "歌う": 183,
      "たがる": 184,
      "許す": 185,
      "がる": 186,
      "訪ねる": 187,
      "始まる": 188,
      "盗む": 189,
      "尋ねる": 190,
      "切る": 191,
      "行ける": 192,
      "失う": 193,
      "慣れる": 194,
      "連れる": 195,
      "多い": 196,
      "認める": 197,
      "長い": 198,
      "学ぶ": 199,
      "変える": 200,
      "進む": 201,
      "調べる": 202,
      "売る": 203,
      "9": 204,
      "離れる": 205,
      "伝える": 206,
      "遅い": 207,
      "ひく": 208,
      "1人": 209,
      "起こす": 210,
      "守る": 211,
      "吸う": 212,
      "過ぎる": 213,
      "若い": 214,
      "少ない": 215,
      "違う": 216,
      "残る": 217,
      "関する": 218,
      "深い": 219,
      "消す": 220,
      "洗う": 221,
      "暮らす": 222,
      "止める": 223,
      "訪れる": 224,
      "続く": 225,
      "受け取る": 226,
      "亡くなる": 227,
      " ": 228,
      ")": 229,
      "気づく": 230,
      "降りる": 231,
      "(": 232,
      "従う": 233,
      "限る": 234,
      "でる": 235,
      "引く": 236,
      "飛ぶ": 237,
      "寒い": 238,
      "飼う": 239,
      "50": 240,
      "欲しい": 241,
      "間に合う": 242,
      "なくす": 243,
      "運ぶ": 244,
      "強い": 245,
      "させる": 246,
      "100": 247,
      "美しい": 248,
      "迎える": 249,
      "すごい": 250,
      "黙る": 251,
      "なくなる": 252,
      "動く": 253,
      "閉める": 254,
      "思い出す": 255,
      "扱う": 256,
      "上げる": 257,
      "望む": 258,
      "たつ": 259,
      "出会う": 260,
      "負ける": 261,
      "暗い": 262,
      "なれる": 263,
      "通う": 264,
      "見つかる": 265,
      "鳴る": 266,
      "かかわる": 267,
      "描く": 268,
      "返す": 269,
      "上がる": 270,
      "逃げる": 271,
      "迷う": 272,
      "いらっしゃる": 273,
      ",": 274,
      "弾く": 275,
      "勝つ": 276,
      "向ける": 277,
      "%": 278,
      "かまう": 279,
      "言える": 280,
      "習う": 281,
      "付ける": 282,
      "難しい": 283,
      "話しかける": 284,
      "怖い": 285,
      "近づく": 286,
      "殺す": 287,
      "渡る": 288,
      "直す": 289,
      "通す": 290,
      "現れる": 291,
      "間違える": 292,
      "空く": 293,
      "12": 294,
      "尽くす": 295,
      "登る": 296,
      "付く": 297,
      "優れる": 298,
      "示す": 299,
      "面白い": 300,
      "太る": 301,
      "断る": 302,
      "きく": 303,
      "残す": 304,
      "増える": 305,
      "消える": 306,
      "打つ": 307,
      "11": 308,
      "正しい": 309,
      "止まる": 310,
      "うれしい": 311,
      "述べる": 312,
      "買える": 313,
      "激しい": 314,
      "曲がる": 315,
      "届く": 316,
      "捨てる": 317,
      "撮る": 318,
      "決まる": 319,
      "付き合う": 320,
      "伺う": 321,
      "15": 322,
      "申し上げる": 323,
      "壊れる": 324,
      "恐れる": 325,
      "恥ずかしい": 326,
      "劣る": 327,
      "える": 328,
      "いでる": 329,
      "落とす": 330,
      "済む": 331,
      "~": 332,
      "泳げる": 333,
      "小さい": 334,
      "通る": 335,
      "含む": 336,
      "しゃべる": 337,
      "耐える": 338,
      "集まる": 339,
      "つれる": 340,
      "はじめる": 341,
      "犯す": 342,
      "話し合う": 343,
      "40": 344,
      "育てる": 345,
      "隠す": 346,
      "集める": 347,
      "会える": 348,
      "輝く": 349,
      "叫ぶ": 350,
      "閉じる": 351,
      "浮かぶ": 352,
      "割る": 353,
      "受け入れる": 354,
      "晴れる": 355,
      "足りる": 356,
      "塗る": 357,
      "去る": 358,
      "泊まる": 359,
      "奪う": 360,
      "達する": 361,
      "踊る": 362,
      "落ち着く": 363,
      "祈る": 364,
      "使える": 365,
      "避ける": 366,
      "り": 367,
      "押す": 368,
      "建てる": 369,
      "脱ぐ": 370,
      "合わせる": 371,
      "倒れる": 372,
      "無い": 373,
      "たずねる": 374,
      "表す": 375,
      "頑張る": 376,
      "招く": 377,
      "愛す": 378,
      "壊す": 379,
      "つまる": 380,
      "暑い": 381,
      ".": 382,
      "見つめる": 383,
      "思える": 384,
      "見かける": 385,
      "支払う": 386,
      "つかむ": 387,
      "詳しい": 388,
      "だます": 389,
      "戦う": 390,
      "だす": 391,
      "破る": 392,
      "回る": 393,
      "暖かい": 394,
      "眠れる": 395,
      "備える": 396,
      "上手い": 397,
      "捜す": 398,
      "聴く": 399,
      "切れる": 400,
      "かぶる": 401,
      "痛い": 402,
      "抱く": 403,
      "振る": 404,
      "思い出せる": 405,
      "好む": 406,
      "吹く": 407,
      "気付く": 408,
      "通ずる": 409,
      "加える": 410,
      "あきらめる": 411,
      "比べる": 412,
      "読める": 413,
      "育つ": 414,
      "向く": 415,
      "解く": 416,
      "歩ける": 417,
      "折る": 418,
      "かねる": 419,
      "痛む": 420,
      "燃える": 421,
      "当たる": 422,
      "謝る": 423,
      "召し上がる": 424,
      "似合う": 425,
      "別れる": 426,
      "減る": 427,
      "1日": 428,
      "疑う": 429,
      "知れる": 430,
      "下がる": 431,
      "乗せる": 432,
      "捕まえる": 433,
      "頼る": 434,
      "微笑む": 435,
      "雇う": 436,
      "かく": 437,
      "いれる": 438,
      "応ずる": 439,
      "沈む": 440,
      "任せる": 441,
      "立ち上がる": 442,
      "見知る": 443,
      "安い": 444,
      "知り合う": 445,
      "解ける": 446,
      "腐る": 447,
      "投げる": 448,
      "悲しい": 449,
      "勧める": 450,
      "流れる": 451,
      "果たす": 452,
      "辞める": 453,
      "短い": 454,
      "らしい": 455,
      "つなぐ": 456,
      "覆う": 457,
      "もたらす": 458,
      "触れる": 459,
      "構う": 460,
      "明るい": 461,
      "焼く": 462,
      "掛ける": 463,
      "すく": 464,
      "並ぶ": 465,
      "狂う": 466,
      "語る": 467,
      "立ち寄る": 468,
      "抱える": 469,
      "告げる": 470,
      "隠れる": 471,
      "閉まる": 472,
      "かなう": 473,
      "取れる": 474,
      "叱る": 475,
      "参る": 476,
      "関わる": 477,
      "なす": 478,
      "頂ける": 479,
      "おっしゃる": 480,
      "ばかげる": 481,
      "好く": 482,
      "嬉しい": 483,
      "書き留める": 484,
      "つづける": 485,
      "遠い": 486,
      "除く": 487,
      "つくる": 488,
      "流す": 489,
      "眠い": 490,
      "やさしい": 491,
      "苦しむ": 492,
      "渡す": 493,
      "たまる": 494,
      "包む": 495,
      "誘う": 496,
      "命ずる": 497,
      "18": 498,
      "致す": 499,
      "引っ越す": 500,
      "治る": 501,
      "責める": 502,
      "襲う": 503,
      "居る": 504,
      "片付ける": 505,
      "a": 506,
      "分ける": 507,
      "からかう": 508,
      "たたく": 509,
      "しる": 510,
      "浴びる": 511,
      "救う": 512,
      "思いつく": 513,
      "酔う": 514,
      "がんばる": 515,
      "伸ばす": 516,
      "覚める": 517,
      "おもしろい": 518,
      "越える": 519,
      "あける": 520,
      "なり": 521,
      "あう": 522,
      "動かす": 523,
      "赤い": 524,
      "CD": 525,
      "及ぶ": 526,
      "取り戻す": 527,
      "おいしい": 528,
      "500": 529,
      "回す": 530,
      "繰り返す": 531,
      "新しい": 532,
      "頂く": 533,
      "重い": 534,
      "勤める": 535,
      "たてる": 536,
      "きれる": 537,
      "訳す": 538,
      "引き起こす": 539,
      "追いつく": 540,
      "確かめる": 541,
      "遭う": 542,
      "診る": 543,
      "数える": 544,
      "名づける": 545,
      "とく": 546,
      "優しい": 547,
      "とれる": 548,
      "あく": 549,
      "わたる": 550,
      ":": 551,
      "嫌う": 552,
      "抜く": 553,
      "きる": 554,
      "基づく": 555,
      "ほしい": 556,
      "存ずる": 557,
      "試す": 558,
      "努める": 559,
      "撃つ": 560,
      "申す": 561,
      "200": 562,
      "欠ける": 563,
      "悩む": 564,
      "訴える": 565,
      "負う": 566,
      "覚ます": 567,
      "代わる": 568,
      "仕上げる": 569,
      "殴る": 570,
      "追う": 571,
      "預ける": 572,
      "磨く": 573,
      "暮れる": 574,
      "結ぶ": 575,
      "転ぶ": 576,
      "咲く": 577,
      "越す": 578,
      "異なる": 579,
      "乗れる": 580,
      "用いる": 581,
      "当てる": 582,
      "くつろぐ": 583,
      "tatoeba": 584,
      "＂": 585,
      "満ちる": 586,
      "追いかける": 587,
      "眺める": 588,
      "はく": 589,
      "抑える": 590,
      "1万": 591,
      "傷つける": 592,
      "寄る": 593,
      "広い": 594,
      "はいる": 595,
      "汚れる": 596,
      "25": 597,
      "誓う": 598,
      "組む": 599,
      "60": 600,
      "超える": 601,
      "囲む": 602,
      "軽い": 603,
      "みなす": 604,
      "経つ": 605,
      "立ち去る": 606,
      "000": 607,
      "贈る": 608,
      "引き受ける": 609,
      "厳しい": 610,
      "触る": 611,
      "やむ": 612,
      "張る": 613,
      "混む": 614,
      "おもう": 615,
      "広まる": 616,
      "すぐれる": 617,
      "1000": 618,
      "勝てる": 619,
      "挙げる": 620,
      "恵まれる": 621,
      "富む": 622,
      "巻き込む": 623,
      "履く": 624,
      "費やす": 625,
      "戻す": 626,
      "有る": 627,
      "16": 628,
      "飽きる": 629,
      "やすい": 630,
      "要る": 631,
      "昇る": 632,
      "しかる": 633,
      "飛び出す": 634,
      "さがす": 635,
      "かかれる": 636,
      "諦める": 637,
      "たり": 638,
      "濡れる": 639,
      "生ずる": 640,
      "さらす": 641,
      "祝う": 642,
      "片づける": 643,
      "貧しい": 644,
      "広がる": 645,
      "裏切る": 646,
      "取り出す": 647,
      "名付ける": 648,
      "下す": 649,
      "試みる": 650,
      "加わる": 651,
      "抜ける": 652,
      "伸びる": 653,
      "効く": 654,
      "恥じる": 655,
      "弾ける": 656,
      "罰する": 657,
      "寂しい": 658,
      "逃げ出す": 659,
      "握る": 660,
      "ほめる": 661,
      "養う": 662,
      "賢い": 663,
      "ふける": 664,
      "生まれつく": 665,
      "甘い": 666,
      "目指す": 667,
      "あがる": 668,
      "助かる": 669,
      "演ずる": 670,
      "絶える": 671,
      "まいる": 672,
      "白い": 673,
      "下げる": 674,
      "稼ぐ": 675,
      "迫る": 676,
      "あたる": 677,
      "こぼす": 678,
      "注ぐ": 679,
      "震える": 680,
      "造る": 681,
      "滑る": 682,
      "預かる": 683,
      "持ち上げる": 684,
      "割れる": 685,
      "適する": 686,
      "解る": 687,
      "ぶつかる": 688,
      "おかしい": 689,
      "あふれる": 690,
      "早し": 691,
      "横切る": 692,
      "80": 693,
      "低い": 694,
      "載る": 695,
      "取り除く": 696,
      "無くす": 697,
      "噛む": 698,
      "立ち止まる": 699,
      "みえる": 700,
      "横たわる": 701,
      "遅し": 702,
      "沿う": 703,
      "下ろす": 704,
      "振り返る": 705,
      "親しい": 706,
      "凍る": 707,
      "控える": 708,
      "引っ張る": 709,
      "13": 710,
      "弱い": 711,
      "痛める": 712,
      "吠える": 713,
      "踏む": 714,
      "70": 715,
      "見送る": 716,
      "17": 717,
      "発つ": 718,
      "ぬれる": 719,
      "もどる": 720,
      "成り立つ": 721,
      "負える": 722,
      "浮かべる": 723,
      "飛び込む": 724,
      "飾る": 725,
      "成し遂げる": 726,
      "危うい": 727,
      "よす": 728,
      "すわる": 729,
      "食う": 730,
      "植える": 731,
      "少なし": 732,
      "離す": 733,
      "譲る": 734,
      "つかまる": 735,
      "いえる": 736,
      "支える": 737,
      "減らす": 738,
      "売れる": 739,
      "渇く": 740,
      "差し上げる": 741,
      "届ける": 742,
      "かむ": 743,
      "捧げる": 744,
      "うかがう": 745,
      "屈する": 746,
      "陥る": 747,
      "つぶす": 748,
      "つくす": 749,
      "振る舞う": 750,
      "刺す": 751,
      "旨い": 752,
      "よこす": 753,
      "通り過ぎる": 754,
      "刈る": 755,
      "蹴る": 756,
      "うるさい": 757,
      "騙す": 758,
      "いらしゃる": 759,
      "拾う": 760,
      "掘る": 761,
      "揺れる": 762,
      "下る": 763,
      "満たす": 764,
      "やせる": 765,
      "24": 766,
      "乗り換える": 767,
      "したがう": 768,
      "見回す": 769,
      "む": 770,
      "外す": 771,
      "おおう": 772,
      "100万": 773,
      "目覚める": 774,
      "よろしい": 775,
      "傷つく": 776,
      "話し掛ける": 777,
      "誉める": 778,
      "締める": 779,
      "捕まる": 780,
      "打ち明ける": 781,
      "青い": 782,
      "悩ます": 783,
      "19": 784,
      "傾ける": 785,
      "論ずる": 786,
      "取り上げる": 787,
      "てく": 788,
      "放す": 789,
      "歩き回る": 790,
      "待たす": 791,
      "冷える": 792,
      "痩せる": 793,
      "申し込む": 794,
      "まちがう": 795,
      "まとめる": 796,
      "こたえる": 797,
      "延ばす": 798,
      "きつい": 799,
      "使い果たす": 800,
      "取り組む": 801,
      "狭い": 802,
      "かわる": 803,
      "b": 804,
      "整える": 805,
      "かえる": 806,
      "禁ずる": 807,
      "抱きしめる": 808,
      "書ける": 809,
      "配る": 810,
      "悲しむ": 811,
      "すませる": 812,
      "見失う": 813,
      "1度": 814,
      "恐い": 815,
      "広げる": 816,
      "21": 817,
      "みせる": 818,
      "就く": 819,
      "喋る": 820,
      "課する": 821,
      "見守る": 822,
      "引き継ぐ": 823,
      "降ろす": 824,
      "漏れる": 825,
      "通り抜ける": 826,
      "観る": 827,
      "曇る": 828,
      "ねがう": 829,
      "詰める": 830,
      "反する": 831,
      "貰う": 832,
      "空ける": 833,
      "ぶつける": 834,
      "衰える": 835,
      "すばらしい": 836,
      "冷たい": 837,
      "接する": 838,
      "熱い": 839,
      "年老いる": 840,
      "怠ける": 841,
      "飲める": 842,
      "並べる": 843,
      "やがる": 844,
      "保つ": 845,
      "なし": 846,
      "青ざめる": 847,
      "貯める": 848,
      "押し入る": 849,
      "止む": 850,
      "厚い": 851,
      "Tシャツ": 852,
      "ふる": 853,
      "分かれる": 854,
      "乾く": 855,
      "流行る": 856,
      "誤る": 857,
      "問う": 858,
      "涼しい": 859,
      "見上げる": 860,
      "騒ぐ": 861,
      "生える": 862,
      "みつける": 863,
      "成る": 864,
      "見逃す": 865,
      "掛かる": 866,
      "とどまる": 867,
      "産む": 868,
      "来れる": 869,
      "待てる": 870,
      "催す": 871,
      "貼る": 872,
      "叩く": 873,
      "生む": 874,
      "かわいい": 875,
      "恐ろしい": 876,
      "収める": 877,
      "すすめる": 878,
      "こわい": 879,
      "45": 880,
      "溺れる": 881,
      "惹く": 882,
      "承る": 883,
      "90": 884,
      "14": 885,
      "吐く": 886,
      "まつ": 887,
      "替える": 888,
      "づける": 889,
      "申し出る": 890,
      "飢える": 891,
      "乗り込む": 892,
      "進める": 893,
      "さす": 894,
      "とまる": 895,
      "取り消す": 896,
      "すばやい": 897,
      "上る": 898,
      "はねる": 899,
      "冒す": 900,
      "c": 901,
      "薄い": 902,
      "悟る": 903,
      "よし": 904,
      "のる": 905,
      "生かす": 906,
      "飛ばす": 907,
      "狙う": 908,
      "亡くす": 909,
      "すごす": 910,
      "折れる": 911,
      "受かる": 912,
      "込める": 913,
      "鳴く": 914,
      "食べ過ぎる": 915,
      "落ち込む": 916,
      "無くなる": 917,
      "面する": 918,
      "つかまえる": 919,
      "手放す": 920,
      "美味しい": 921,
      "怠る": 922,
      "素早い": 923,
      "酔っ払う": 924,
      "つながる": 925,
      "逆らう": 926,
      "はやる": 927,
      "固い": 928,
      "きける": 929,
      "取り替える": 930,
      "叶う": 931,
      "ためる": 932,
      "蓄える": 933,
      "拒む": 934,
      "さわる": 935,
      "くだる": 936,
      "光る": 937,
      "慌てる": 938,
      "しめる": 939,
      "賭ける": 940,
      "300": 941,
      "当てはまる": 942,
      "漏らす": 943,
      "利く": 944,
      "呼び出す": 945,
      "役立つ": 946,
      "移る": 947,
      "思い切る": 948,
      "焼ける": 949,
      "古い": 950,
      "出せる": 951,
      "とめる": 952,
      "あわてる": 953,
      "ふさがる": 954,
      "見分ける": 955,
      "着ける": 956,
      "楽しめる": 957,
      "増す": 958,
      "2000": 959,
      "枯れる": 960,
      "走れる": 961,
      "泊める": 962,
      "見なす": 963,
      "ちなむ": 964,
      "決する": 965,
      "積む": 966,
      "計る": 967,
      "免れる": 968,
      "留める": 969,
      "うなずく": 970,
      "切らす": 971,
      "ためらう": 972,
      "憎む": 973,
      "切り倒す": 974,
      "熟する": 975,
      "害する": 976,
      "まわる": 977,
      "果てる": 978,
      "務める": 979,
      "励ます": 980,
      "めぐる": 981,
      "押さえる": 982,
      "おびえる": 983,
      "はずす": 984,
      "愛し合う": 985,
      "恐れ入る": 986,
      "こわれる": 987,
      "22": 988,
      "含める": 989,
      "UFO": 990,
      "出掛ける": 991,
      "重ねる": 992,
      "ふく": 993,
      "詰まる": 994,
      "働ける": 995,
      "27": 996,
      "やり遂げる": 997,
      "着替える": 998,
      "おぼれる": 999,
      "馬鹿げる": 1000,
      "助け合う": 1001,
      "外れる": 1002,
      "すます": 1003,
      "妨げる": 1004,
      "持ち合わせる": 1005,
      "拾い上げる": 1006,
      "寝込む": 1007,
      "振り向く": 1008,
      "はまる": 1009,
      "1990": 1010,
      "味わう": 1011,
      "返る": 1012,
      "損なう": 1013,
      "たどり着く": 1014,
      "立ち直る": 1015,
      "属する": 1016,
      "おごる": 1017,
      "打ち上げる": 1018,
      "31": 1019,
      "手渡す": 1020,
      "恋しい": 1021,
      "燃やす": 1022,
      "はかどる": 1023,
      "うける": 1024,
      "付け加える": 1025,
      "至る": 1026,
      "脅す": 1027,
      "やれる": 1028,
      "持ち帰る": 1029,
      "サボる": 1030,
      "見下す": 1031,
      "足る": 1032,
      "占める": 1033,
      "閉じ込める": 1034,
      "発する": 1035,
      "取り扱う": 1036,
      "移す": 1037,
      "たやすい": 1038,
      "出くわす": 1039,
      "おこる": 1040,
      "見当たる": 1041,
      "はやい": 1042,
      "増やす": 1043,
      "割り当てる": 1044,
      "召す": 1045,
      "おきる": 1046,
      "おさまる": 1047,
      "思い付く": 1048,
      "ささげる": 1049,
      "取り計らう": 1050,
      "突っ込む": 1051,
      "差し出す": 1052,
      "見積もる": 1053,
      "しみる": 1054,
      "ねらう": 1055,
      "おくれる": 1056,
      "交わす": 1057,
      "鳴らす": 1058,
      "遊べる": 1059,
      "おろす": 1060,
      "引き裂く": 1061,
      "放る": 1062,
      "思いがける": 1063,
      "っぽい": 1064,
      "素晴らしい": 1065,
      "放つ": 1066,
      "いじめる": 1067,
      "しびれる": 1068,
      "泊る": 1069,
      "治す": 1070,
      "/": 1071,
      "ものすごい": 1072,
      "捕らえる": 1073,
      "夢見る": 1074,
      "たべる": 1075,
      "伴う": 1076,
      "染める": 1077,
      "言い張る": 1078,
      "詫びる": 1079,
      "編む": 1080,
      "逃れる": 1081,
      "ほる": 1082,
      "飛び越える": 1083,
      "ちがう": 1084,
      "欲する": 1085,
      "過ぎ去る": 1086,
      "照らす": 1087,
      "寄せる": 1088,
      "冷める": 1089,
      "つきあう": 1090,
      "固める": 1091,
      "込む": 1092,
      "良し": 1093,
      "乗り越える": 1094,
      "見せびらかす": 1095,
      "ふさぐ": 1096,
      "見出す": 1097,
      "縛る": 1098,
      "ふるまう": 1099,
      "もうける": 1100,
      "建つ": 1101,
      "焦る": 1102,
      "明かす": 1103,
      "聞き取れる": 1104,
      "逃す": 1105,
      "載せる": 1106,
      "築く": 1107,
      "成す": 1108,
      "巻く": 1109,
      "くっつく": 1110,
      "訊く": 1111,
      "じゃう": 1112,
      "曲げる": 1113,
      "受け付ける": 1114,
      "欠かせる": 1115,
      "倒す": 1116,
      "汚す": 1117,
      "過ごせる": 1118,
      "測る": 1119,
      "かぎる": 1120,
      "のぞく": 1121,
      "取りかかる": 1122,
      "言い表せる": 1123,
      "ふさわしい": 1124,
      "取り壊す": 1125,
      "追いつける": 1126,
      "失くす": 1127,
      "近い": 1128,
      "授ける": 1129,
      "生み出す": 1130,
      "済ます": 1131,
      "引き取る": 1132,
      "目立つ": 1133,
      "弱る": 1134,
      "干す": 1135,
      "150": 1136,
      "とらえる": 1137,
      "刻む": 1138,
      "5万": 1139,
      "0": 1140,
      "混ぜる": 1141,
      "投げつける": 1142,
      "むく": 1143,
      "うぬぼれる": 1144,
      "うつ": 1145,
      "応える": 1146,
      "帰れる": 1147,
      "換える": 1148,
      "明ける": 1149,
      "取り付ける": 1150,
      "歌える": 1151,
      "可愛い": 1152,
      "尽きる": 1153,
      "とがめる": 1154,
      "快い": 1155,
      "さめる": 1156,
      "黒い": 1157,
      "見捨てる": 1158,
      "丸い": 1159,
      "走り去る": 1160,
      "しゃべれる": 1161,
      "飛び上がる": 1162,
      "追い出す": 1163,
      "散らかる": 1164,
      "見張る": 1165,
      "教わる": 1166,
      "しがみつく": 1167,
      "のぼる": 1168,
      "伝わる": 1169,
      "積もる": 1170,
      "あわせる": 1171,
      "はなす": 1172,
      "さえずる": 1173,
      "濃い": 1174,
      "継ぐ": 1175,
      "生き残る": 1176,
      "こらえる": 1177,
      "摘む": 1178,
      "もらす": 1179,
      "澄む": 1180,
      "のむ": 1181,
      "おかす": 1182,
      "報う": 1183,
      "割り込む": 1184,
      "遂げる": 1185,
      "-": 1186,
      "掴む": 1187,
      "高める": 1188,
      "なおす": 1189,
      "闘う": 1190,
      "まく": 1191,
      "みつかる": 1192,
      "堅い": 1193,
      "映る": 1194,
      "近づける": 1195,
      "きまる": 1196,
      "着せる": 1197,
      "はさむ": 1198,
      "ありがたい": 1199,
      "払える": 1200,
      "運べる": 1201,
      "はずれる": 1202,
      "あやうい": 1203,
      "酔っぱらう": 1204,
      "気取る": 1205,
      "漂う": 1206,
      "x": 1207,
      "治まる": 1208,
      "たえる": 1209,
      "のせる": 1210,
      "高まる": 1211,
      "拭く": 1212,
      "向かい合う": 1213,
      "考え直す": 1214,
      "定める": 1215,
      "埋める": 1216,
      "つらい": 1217,
      "辛い": 1218,
      "抜け出す": 1219,
      "めがける": 1220,
      "切り抜ける": 1221,
      "多し": 1222,
      "掲げる": 1223,
      "荒れる": 1224,
      "Eメール": 1225,
      "願える": 1226,
      "防ぐ": 1227,
      "崩す": 1228,
      "1998": 1229,
      "おそい": 1230,
      "そこなう": 1231,
      "響く": 1232,
      "ゆでる": 1233,
      "出迎える": 1234,
      "脱する": 1235,
      "聞ける": 1236,
      "65": 1237,
      "はめる": 1238,
      "見舞う": 1239,
      "轢く": 1240,
      "寝入る": 1241,
      "生まれ育つ": 1242,
      "書き込む": 1243,
      "褒める": 1244,
      "たとえる": 1245,
      "ず": 1246,
      "騒がしい": 1247,
      "薦める": 1248,
      "振舞う": 1249,
      "呼びかける": 1250,
      "儲ける": 1251,
      "おこす": 1252,
      "凝る": 1253,
      "憧れる": 1254,
      "許せる": 1255,
      "敷く": 1256,
      "押し付ける": 1257,
      "溶ける": 1258,
      "はかる": 1259,
      "やむない": 1260,
      "まかせる": 1261,
      "慰める": 1262,
      "もたれる": 1263,
      "ほのめかす": 1264,
      "折り返す": 1265,
      "つとめる": 1266,
      "受け継ぐ": 1267,
      "123": 1268,
      "じみる": 1269,
      "10万": 1270,
      "背負う": 1271,
      "つまずく": 1272,
      "かがめる": 1273,
      "現す": 1274,
      "かじる": 1275,
      "寝そべる": 1276,
      "近寄る": 1277,
      "及ぼす": 1278,
      "1980": 1279,
      "くずす": 1280,
      "食べれる": 1281,
      "冷やす": 1282,
      "ありふれる": 1283,
      "取り合う": 1284,
      "むずかしい": 1285,
      "つめる": 1286,
      "通れる": 1287,
      "持ち出す": 1288,
      "吹き出す": 1289,
      "つかる": 1290,
      "飛べる": 1291,
      "やり直す": 1292,
      "1950": 1293,
      "争う": 1294,
      "とりかかる": 1295,
      "詰め込む": 1296,
      "被る": 1297,
      "唱える": 1298,
      "寝かせる": 1299,
      "さておく": 1300,
      "出でる": 1301,
      "28": 1302,
      "細い": 1303,
      "ごとし": 1304,
      "づく": 1305,
      "釣る": 1306,
      "さえぎる": 1307,
      "ほえる": 1308,
      "かすむ": 1309,
      "投げかける": 1310,
      "瀕する": 1311,
      "こなす": 1312,
      "3000": 1313,
      "吹き飛ばす": 1314,
      "柔らかい": 1315,
      "持ち歩く": 1316,
      "思いとどまる": 1317,
      "浮く": 1318,
      "秘める": 1319,
      "付け込む": 1320,
      "おとなしい": 1321,
      "1960": 1322,
      "居合わせる": 1323,
      "偉い": 1324,
      "さく": 1325,
      "賜る": 1326,
      "甘える": 1327,
      "e": 1328,
      "選べる": 1329,
      "こめる": 1330,
      "覗く": 1331,
      "仕上がる": 1332,
      "しつこい": 1333,
      "判る": 1334,
      "見とれる": 1335,
      "ほほえむ": 1336,
      "とおす": 1337,
      "かき混ぜる": 1338,
      "すすむ": 1339,
      "追い払う": 1340,
      "散る": 1341,
      "喋れる": 1342,
      "35": 1343,
      "ぶらつく": 1344,
      "GNP": 1345,
      "正す": 1346,
      "射る": 1347,
      "言い争う": 1348,
      "m": 1349,
      "下りる": 1350,
      "飲み込む": 1351,
      "d": 1352,
      "隔てる": 1353,
      "のがれる": 1354,
      "指さす": 1355,
      "悔やむ": 1356,
      "捕る": 1357,
      "かう": 1358,
      "苦しい": 1359,
      "立たす": 1360,
      "てらっしゃる": 1361,
      "おりる": 1362,
      "さしあげる": 1363,
      "ふるう": 1364,
      "そろう": 1365,
      "商う": 1366,
      "さびしい": 1367,
      "寝過ごす": 1368,
      "おぼえる": 1369,
      "負かす": 1370,
      "でかける": 1371,
      "等しい": 1372,
      "にくい": 1373,
      "うたう": 1374,
      "仕える": 1375,
      "思い込む": 1376,
      "こわす": 1377,
      "守れる": 1378,
      "連れ出す": 1379,
      "あてる": 1380,
      "よろこぶ": 1381,
      "知らす": 1382,
      "ごまかす": 1383,
      "せがむ": 1384,
      "2万": 1385,
      "くわえる": 1386,
      "摂る": 1387,
      "照る": 1388,
      "心がける": 1389,
      "離せる": 1390,
      "親しむ": 1391,
      "煮る": 1392,
      "ぶる": 1393,
      "立ち入る": 1394,
      "駆ける": 1395,
      "欠く": 1396,
      "や": 1397,
      "和らぐ": 1398,
      "問い合わせる": 1399,
      "はえる": 1400,
      "伏せる": 1401,
      "差し込む": 1402,
      "惜しむ": 1403,
      "軽んずる": 1404,
      "こぐ": 1405,
      "待ち望む": 1406,
      "温める": 1407,
      "あらわす": 1408,
      "さぼる": 1409,
      "勝ち取る": 1410,
      "割く": 1411,
      "舞い上がる": 1412,
      "近付く": 1413,
      "処する": 1414,
      "追い込む": 1415,
      "消え去る": 1416,
      "図る": 1417,
      "なめる": 1418,
      "平らげる": 1419,
      "鍛える": 1420,
      "そろえる": 1421,
      "乗り出す": 1422,
      "伝う": 1423,
      "甘やかす": 1424,
      "硬い": 1425,
      "ける": 1426,
      "奪い取る": 1427,
      "見込む": 1428,
      "動き回る": 1429,
      "取り返す": 1430,
      "しぼる": 1431,
      "省く": 1432,
      "ふれる": 1433,
      "忘れ去る": 1434,
      "まちがえる": 1435,
      "表れる": 1436,
      "幼い": 1437,
      "装う": 1438,
      "めくる": 1439,
      "閉じこもる": 1440,
      "赤らめる": 1441,
      "くつろげる": 1442,
      "もてる": 1443,
      "湿る": 1444,
      "指す": 1445,
      "むかう": 1446,
      "ゆく": 1447,
      "折り合う": 1448,
      "こだわる": 1449,
      "削る": 1450,
      "ねだる": 1451,
      "わずらう": 1452,
      "だまる": 1453,
      "聞き入る": 1454,
      "書き直す": 1455,
      "組み立てる": 1456,
      "ずば抜ける": 1457,
      "在る": 1458,
      "云う": 1459,
      "堪える": 1460,
      "傾く": 1461,
      "95": 1462,
      "終る": 1463,
      "mail": 1464,
      "言い換える": 1465,
      "OK": 1466,
      "見直す": 1467,
      "御座る": 1468,
      "走り回る": 1469,
      "こする": 1470,
      "刺さる": 1471,
      "遣わす": 1472,
      "むける": 1473,
      "取り残す": 1474,
      "きめる": 1475,
      "もてなす": 1476,
      "そらす": 1477,
      "考え出す": 1478,
      "まぬがれる": 1479,
      "整う": 1480,
      "そる": 1481,
      "暖める": 1482,
      "かかえる": 1483,
      "怒鳴る": 1484,
      "かる": 1485,
      "古し": 1486,
      "動ける": 1487,
      "望める": 1488,
      "寄りかかる": 1489,
      "取り囲む": 1490,
      "1939": 1491,
      "5000": 1492,
      "焦げる": 1493,
      "据える": 1494,
      "熱する": 1495,
      "それる": 1496,
      "突き出る": 1497,
      "帰す": 1498,
      "貫く": 1499,
      "於く": 1500,
      "施す": 1501,
      "差す": 1502,
      "吹き込む": 1503,
      "如し": 1504,
      "固まる": 1505,
      "損ねる": 1506,
      "待ちこがれる": 1507,
      "す": 1508,
      "剃る": 1509,
      "待ち焦がれる": 1510,
      "心得る": 1511,
      "見渡す": 1512,
      "ののしる": 1513,
      "かす": 1514,
      "ささやく": 1515,
      "閉ざす": 1516,
      "つぎ込む": 1517,
      "たのむ": 1518,
      "裂ける": 1519,
      "評する": 1520,
      "写す": 1521,
      "50万": 1522,
      "打ち込む": 1523,
      "説き伏せる": 1524,
      "見下ろす": 1525,
      "駆け上がる": 1526,
      "足せる": 1527,
      "くう": 1528,
      "1970": 1529,
      "あてはまる": 1530,
      "すれ違う": 1531,
      "逃がす": 1532,
      "すたれる": 1533,
      "つう": 1534,
      "ABC": 1535,
      "受け持つ": 1536,
      "1999": 1537,
      "易しい": 1538,
      "送れる": 1539,
      "出来上がる": 1540,
      "凄い": 1541,
      "分る": 1542,
      "ともす": 1543,
      "どく": 1544,
      "惚れる": 1545,
      "k": 1546,
      "持てる": 1547,
      "はれる": 1548,
      "先立つ": 1549,
      "眠たい": 1550,
      "絞る": 1551,
      "かみつく": 1552,
      "導く": 1553,
      "さらう": 1554,
      "取り入れる": 1555,
      "企てる": 1556,
      "駆けつける": 1557,
      "書き上げる": 1558,
      "おどろく": 1559,
      "まにあう": 1560,
      "うつす": 1561,
      "引き返す": 1562,
      "逃げ去る": 1563,
      "飲ます": 1564,
      "ひっくり返す": 1565,
      "次ぐ": 1566,
      "設ける": 1567,
      "おしえる": 1568,
      "ぶつ": 1569,
      "促す": 1570,
      "がかる": 1571,
      "よぶ": 1572,
      "すべる": 1573,
      "挑む": 1574,
      "収まる": 1575,
      "引き出す": 1576,
      "締め出す": 1577,
      "慎む": 1578,
      "きこえる": 1579,
      "冴える": 1580,
      "強める": 1581,
      "よろめく": 1582,
      "先んずる": 1583,
      "26": 1584,
      "肥える": 1585,
      "生やす": 1586,
      "点ける": 1587,
      "代える": 1588,
      "若し": 1589,
      "2千": 1590,
      "営む": 1591,
      "こぼれる": 1592,
      "崩れる": 1593,
      "かなえる": 1594,
      "言いつける": 1595,
      "退く": 1596,
      "なびく": 1597,
      "わすれる": 1598,
      "つぶれる": 1599,
      "飛び去る": 1600,
      "眠り込む": 1601,
      "ふくらむ": 1602,
      "利ける": 1603,
      "うらやむ": 1604,
      "薄れる": 1605,
      "取り付く": 1606,
      "まわす": 1607,
      "ひざまずく": 1608,
      "よみがえる": 1609,
      "打ち勝つ": 1610,
      "うらやましい": 1611,
      "物語る": 1612,
      "報ずる": 1613,
      "語り合う": 1614,
      "切り開く": 1615,
      "働かす": 1616,
      "改める": 1617,
      "聞き入れる": 1618,
      "温かい": 1619,
      "ひそめる": 1620,
      "嘆く": 1621,
      "見落とす": 1622,
      "添える": 1623,
      "180": 1624,
      "砕ける": 1625,
      "掘り出す": 1626,
      "浅い": 1627,
      "まける": 1628,
      "f": 1629,
      "400": 1630,
      "つかえる": 1631,
      "住める": 1632,
      "たる": 1633,
      "湧く": 1634,
      "赦す": 1635,
      "・": 1636,
      "経る": 1637,
      "まくる": 1638,
      "ほどける": 1639,
      "付き添う": 1640,
      "こもる": 1641,
      "嗅ぎつける": 1642,
      "押し流す": 1643,
      "聞き飽きる": 1644,
      "はる": 1645,
      "使い古す": 1646,
      "腰掛ける": 1647,
      "おさえる": 1648,
      "ふえる": 1649,
      "つる": 1650,
      "おえる": 1651,
      "つかう": 1652,
      "はう": 1653,
      "通りかかる": 1654,
      "おさめる": 1655,
      "蒸し暑い": 1656,
      "5千": 1657,
      "あたえる": 1658,
      "差し支える": 1659,
      "擦る": 1660,
      "めく": 1661,
      "1945": 1662,
      "通りぬける": 1663,
      "かぶれる": 1664,
      "受け取れる": 1665,
      "ひる": 1666,
      "驚かす": 1667,
      "l": 1668,
      "かわく": 1669,
      "敬う": 1670,
      "足す": 1671,
      "盗る": 1672,
      "とける": 1673,
      "行き詰まる": 1674,
      "s": 1675,
      "臨む": 1676,
      "30万": 1677,
      "揃う": 1678,
      "ながめる": 1679,
      "まずい": 1680,
      "ちまう": 1681,
      "+": 1682,
      "やぶる": 1683,
      "追いつめる": 1684,
      "飛び降りる": 1685,
      ";": 1686,
      "押し分ける": 1687,
      "あきれる": 1688,
      "差し伸べる": 1689,
      "乱れる": 1690,
      "3万": 1691,
      "苦しめる": 1692,
      "要する": 1693,
      "練る": 1694,
      "たどる": 1695,
      "引っかかる": 1696,
      "獲る": 1697,
      "敗れる": 1698,
      "はたく": 1699,
      "沸く": 1700,
      "亡し": 1701,
      "脅かす": 1702,
      "やかましい": 1703,
      "寝かしつける": 1704,
      "呼び戻す": 1705,
      "そびえる": 1706,
      "食らう": 1707,
      "1億": 1708,
      "泣き崩れる": 1709,
      "飲み干す": 1710,
      "破れる": 1711,
      "停める": 1712,
      "縫う": 1713,
      "仰ぐ": 1714,
      "ひっぱたく": 1715,
      "ほてる": 1716,
      "細かい": 1717,
      "のける": 1718,
      "魅する": 1719,
      "吹き消す": 1720,
      "飛びつく": 1721,
      "押し開ける": 1722,
      "裂く": 1723,
      "結び付ける": 1724,
      "泣き止む": 1725,
      "引き上げる": 1726,
      "とがる": 1727,
      "膨らむ": 1728,
      "切りつめる": 1729,
      "あざ笑う": 1730,
      "黄色い": 1731,
      "とおる": 1732,
      "ゆずる": 1733,
      "励む": 1734,
      "行かす": 1735,
      "切り取る": 1736,
      "投げ込む": 1737,
      "帯びる": 1738,
      "滅ぼす": 1739,
      "作り上げる": 1740,
      "ばれる": 1741,
      "ふざける": 1742,
      "傷付ける": 1743,
      "800": 1744,
      "燃え上がる": 1745,
      "押し寄せる": 1746,
      "忍び寄る": 1747,
      "噛み付く": 1748,
      "曲がりくねる": 1749,
      "おける": 1750,
      "持ち込む": 1751,
      "乗り捨てる": 1752,
      "写る": 1753,
      "づらい": 1754,
      "組み込む": 1755,
      "危ない": 1756,
      "表せる": 1757,
      "ほおばる": 1758,
      "埋まる": 1759,
      "古びる": 1760,
      "UN": 1761,
      "AND": 1762,
      "ゐる": 1763,
      "売り出す": 1764,
      "きたす": 1765,
      "揃える": 1766,
      "23": 1767,
      "乗り切る": 1768,
      "2001": 1769,
      "阻む": 1770,
      "ひろう": 1771,
      "ちかづく": 1772,
      "便る": 1773,
      "替わる": 1774,
      "まとう": 1775,
      "なだめる": 1776,
      "留まる": 1777,
      "たたむ": 1778,
      "分け合う": 1779,
      "乾かす": 1780,
      "見合わせる": 1781,
      "渡れる": 1782,
      "泣きやむ": 1783,
      "おくる": 1784,
      "つき合う": 1785,
      "ともなう": 1786,
      "障る": 1787,
      "覗き込む": 1788,
      "めざす": 1789,
      "漕ぐ": 1790,
      "暮す": 1791,
      "科する": 1792,
      "企む": 1793,
      "1941": 1794,
      "しらべる": 1795,
      "申しあげる": 1796,
      "変る": 1797,
      "取り寄せる": 1798,
      "けり": 1799,
      "患う": 1800,
      "兼ねる": 1801,
      "ひきつける": 1802,
      "案ずる": 1803,
      "流れ落ちる": 1804,
      "120": 1805,
      "込み入る": 1806,
      "訳せる": 1807,
      "書き取る": 1808,
      "いたる": 1809,
      "貰える": 1810,
      "照れる": 1811,
      "見合う": 1812,
      "p": 1813,
      "75": 1814,
      "入り込む": 1815,
      "取りやめる": 1816,
      "怪しい": 1817,
      "遠し": 1818,
      "溢れる": 1819,
      "こえる": 1820,
      "つつく": 1821,
      "聞かす": 1822,
      "頷く": 1823,
      "鈍る": 1824,
      "わきまえる": 1825,
      "弱まる": 1826,
      "たのしい": 1827,
      "作れる": 1828,
      "そそのかす": 1829,
      "1997": 1830,
      "飛びかかる": 1831,
      "寝れる": 1832,
      "妬む": 1833,
      "おれる": 1834,
      "みがく": 1835,
      "束ねる": 1836,
      "訊ねる": 1837,
      "重なる": 1838,
      "はげる": 1839,
      "たれる": 1840,
      "満ち溢れる": 1841,
      "押しのける": 1842,
      "吹きかける": 1843,
      "立ちあがる": 1844,
      "もがく": 1845,
      "つぶる": 1846,
      "抱きつく": 1847,
      "そむける": 1848,
      "休める": 1849,
      "ねたむ": 1850,
      "はねつける": 1851,
      "うろたえる": 1852,
      "引き付ける": 1853,
      "さます": 1854,
      "表わす": 1855,
      "面食らう": 1856,
      "察する": 1857,
      "退ける": 1858,
      "説く": 1859,
      "あこがれる": 1860,
      "探し求める": 1861,
      "いかす": 1862,
      "かき分ける": 1863,
      "まとまる": 1864,
      "打ち負かす": 1865,
      "送り出す": 1866,
      "くずれる": 1867,
      "でっち上げる": 1868,
      "澄ます": 1869,
      "量る": 1870,
      "極める": 1871,
      "生き返る": 1872,
      "あせる": 1873,
      "食べすぎる": 1874,
      "謹む": 1875,
      "厚かましい": 1876,
      "窮する": 1877,
      "かりる": 1878,
      "しでかす": 1879,
      "のぞきこむ": 1880,
      "溶かす": 1881,
      "かせぐ": 1882,
      "たのしむ": 1883,
      "とどめる": 1884,
      "見習う": 1885,
      "54": 1886,
      "たかる": 1887,
      "10億": 1888,
      "鳴り響く": 1889,
      "延びる": 1890,
      "NTT": 1891,
      "言い渡す": 1892,
      "もつれる": 1893,
      "仕方ない": 1894,
      "投げ出す": 1895,
      "売り切れる": 1896,
      "見付かる": 1897,
      "癒す": 1898,
      "いじる": 1899,
      "できあがる": 1900,
      "119": 1901,
      "CM": 1902,
      "噛みつく": 1903,
      "110": 1904,
      "酸っぱい": 1905,
      "見渡せる": 1906,
      "盛り上がる": 1907,
      "さし上げる": 1908,
      "き": 1909,
      "栄える": 1910,
      "償う": 1911,
      "いやしい": 1912,
      "戴ける": 1913,
      "切り出す": 1914,
      "使いこなせる": 1915,
      "組み合わせる": 1916,
      "辿り着く": 1917,
      "引き抜く": 1918,
      "有難い": 1919,
      "従える": 1920,
      "断ずる": 1921,
      "珍しい": 1922,
      "称する": 1923,
      "さえる": 1924,
      "散らかす": 1925,
      "仕立てる": 1926,
      "のばす": 1927,
      "切り分ける": 1928,
      "とぶ": 1929,
      "あかす": 1930,
      "はたらく": 1931,
      "選び出す": 1932,
      "落ち着ける": 1933,
      "書き写す": 1934,
      "駆け込む": 1935,
      "とりつく": 1936,
      "歩み寄る": 1937,
      "ぬく": 1938,
      "送り返す": 1939,
      "実る": 1940,
      "青白い": 1941,
      "ゆれる": 1942,
      "#": 1943,
      "STL": 1944,
      "しく": 1945,
      "39": 1946,
      "飲み込める": 1947,
      "ひっかかる": 1948,
      "久しい": 1949,
      "落っこちる": 1950,
      "1987": 1951,
      "ググる": 1952,
      "繋がる": 1953,
      "すっごい": 1954,
      "苛立つ": 1955,
      "操る": 1956,
      "転がる": 1957,
      "委ねる": 1958,
      "あしらう": 1959,
      "くだける": 1960,
      "害す": 1961,
      "採る": 1962,
      "掻く": 1963,
      "OL": 1964,
      "散らばる": 1965,
      "たゆむ": 1966,
      "芽生える": 1967,
      "切り離す": 1968,
      "もれる": 1969,
      "置ける": 1970,
      "飛び乗る": 1971,
      "思い悩む": 1972,
      "染まる": 1973,
      "からむ": 1974,
      "ぬかるむ": 1975,
      "積み上げる": 1976,
      "引き続く": 1977,
      "炊く": 1978,
      "H": 1979,
      "静まる": 1980,
      "志す": 1981,
      "わく": 1982,
      "老いる": 1983,
      "あやす": 1984,
      "踏み出す": 1985,
      "消え失せる": 1986,
      "おちる": 1987,
      "緩める": 1988,
      "とびぬける": 1989,
      "寝つく": 1990,
      "静まり返る": 1991,
      "乗っ取る": 1992,
      "200万": 1993,
      "上回る": 1994,
      "言い聞かせる": 1995,
      "またがる": 1996,
      "呼び起こす": 1997,
      "かたづける": 1998,
      "ぬぐ": 1999,
      "かつぐ": 2000,
      "運び出す": 2001,
      "取っ組む": 2002,
      "言い当てる": 2003,
      "羨ましい": 2004,
      "忍ぶ": 2005,
      "切り詰める": 2006,
      "知れ渡る": 2007,
      "おちいる": 2008,
      "ひったくる": 2009,
      "連れ去る": 2010,
      "にらむ": 2011,
      "罵る": 2012,
      "まごつく": 2013,
      "もたれかかる": 2014,
      "震わせる": 2015,
      "病む": 2016,
      "もどす": 2017,
      "なく": 2018,
      "さまよう": 2019,
      "嘆き悲しむ": 2020,
      "携わる": 2021,
      "貯える": 2022,
      "はずかしい": 2023,
      "泡立てる": 2024,
      "旅立つ": 2025,
      "臭い": 2026,
      "ずばぬける": 2027,
      "構える": 2028,
      "いだく": 2029,
      "取り掛かる": 2030,
      "はなれる": 2031,
      "あやまる": 2032,
      "果たせる": 2033,
      "省ける": 2034,
      "なぐる": 2035,
      "おだてる": 2036,
      "くむ": 2037,
      "行なう": 2038,
      "いがみ合う": 2039,
      "引き渡す": 2040,
      "荒らす": 2041,
      "たくらむ": 2042,
      "待ちわびる": 2043,
      "産まれる": 2044,
      "向う": 2045,
      "たたえる": 2046,
      "呆れる": 2047,
      "引きずる": 2048,
      "開け放す": 2049,
      "待ち受ける": 2050,
      "囁く": 2051,
      "偽る": 2052,
      "打ち解ける": 2053,
      "こる": 2054,
      "むなしい": 2055,
      "500万": 2056,
      "おとす": 2057,
      "見破る": 2058,
      "はらう": 2059,
      "任す": 2060,
      "ひるむ": 2061,
      "しくじる": 2062,
      "押し込む": 2063,
      "骨折る": 2064,
      "なじめる": 2065,
      "煮える": 2066,
      "起き上がる": 2067,
      "転げ落ちる": 2068,
      "そう": 2069,
      "飼い慣らす": 2070,
      "見付ける": 2071,
      "なまける": 2072,
      "はしる": 2073,
      "くわしい": 2074,
      "思い浮かべる": 2075,
      "早まる": 2076,
      "直る": 2077,
      "かぐ": 2078,
      "あつかましい": 2079,
      "SF": 2080,
      "DJ": 2081,
      "くわす": 2082,
      "混み合う": 2083,
      "巻き起こす": 2084,
      "当る": 2085,
      "添う": 2086,
      "やらかす": 2087,
      "和らげる": 2088,
      "くじける": 2089,
      "学べる": 2090,
      "g": 2091,
      "ゆるす": 2092,
      "ほうる": 2093,
      "こまる": 2094,
      "流れ出す": 2095,
      "給う": 2096,
      "指差す": 2097,
      "1492": 2098,
      "創る": 2099,
      "講ずる": 2100,
      "探る": 2101,
      "呈する": 2102,
      "ゆるい": 2103,
      "吸い込む": 2104,
      "騒々しい": 2105,
      "ほどく": 2106,
      "ひける": 2107,
      "こねる": 2108,
      "43": 2109,
      "突き止める": 2110,
      "治める": 2111,
      "かえす": 2112,
      "結べる": 2113,
      "かしこまる": 2114,
      "言ふ": 2115,
      "出会える": 2116,
      "EC": 2117,
      "N": 2118,
      "farshad": 2119,
      "よせる": 2120,
      "CC": 2121,
      "わる": 2122,
      "ころぶ": 2123,
      "腹立つ": 2124,
      "OS": 2125,
      "強いる": 2126,
      "300万": 2127,
      "しかり": 2128,
      "つのる": 2129,
      "鋭い": 2130,
      "=": 2131,
      "余る": 2132,
      "隠せる": 2133,
      "立ち向かう": 2134,
      "ひっかく": 2135,
      "いそがしい": 2136,
      "PC": 2137,
      "飛び立つ": 2138,
      "みすぼらしい": 2139,
      "顧みる": 2140,
      "重たい": 2141,
      "かわす": 2142,
      "生く": 2143,
      "つぐ": 2144,
      "ふとる": 2145,
      "語りかける": 2146,
      "凝らす": 2147,
      "にげる": 2148,
      "さける": 2149,
      "うろつく": 2150,
      "待ちかまえる": 2151,
      "20億": 2152,
      "あそぶ": 2153,
      "1920": 2154,
      "傷む": 2155,
      "1111": 2156,
      "32": 2157,
      "放せる": 2158,
      "戻れる": 2159,
      "伺える": 2160,
      "置き換える": 2161,
      "泡立つ": 2162,
      "喜ばしい": 2163,
      "おわる": 2164,
      "募る": 2165,
      "歩む": 2166,
      "ひきとる": 2167,
      "押し出す": 2168,
      "使い切る": 2169,
      "書き出す": 2170,
      "突き進む": 2171,
      "HAVE": 2172,
      "立ちこめる": 2173,
      "はぐれる": 2174,
      "炒める": 2175,
      "記す": 2176,
      "y": 2177,
      "撥ねる": 2178,
      "のこす": 2179,
      "いきる": 2180,
      "おそれる": 2181,
      "見抜く": 2182,
      "欠かす": 2183,
      "「": 2184,
      "」": 2185,
      "尖る": 2186,
      "ぶっちゃける": 2187,
      "恵む": 2188,
      "塞がる": 2189,
      "煩わしい": 2190,
      "生れる": 2191,
      "ならぶ": 2192,
      "乱す": 2193,
      "かき集める": 2194,
      "ならす": 2195,
      "茹でる": 2196,
      "欺く": 2197,
      "乗り上げる": 2198,
      "かすめる": 2199,
      "うばう": 2200,
      "とらわれる": 2201,
      "思いだす": 2202,
      "たわむ": 2203,
      "探し出す": 2204,
      "立ち込める": 2205,
      "つかめる": 2206,
      "みつめる": 2207,
      "嗅ぐ": 2208,
      "せびる": 2209,
      "見れる": 2210,
      "かぞえる": 2211,
      "あらう": 2212,
      "売り払う": 2213,
      "jl": 2214,
      "抱き合う": 2215,
      "かれる": 2216,
      "どなる": 2217,
      "並外れる": 2218,
      "ALS": 2219,
      "討つ": 2220,
      "でっちあげる": 2221,
      "忍び込む": 2222,
      "あらわれる": 2223,
      "そっけない": 2224,
      "つきまとう": 2225,
      "抱え込む": 2226,
      "焦がす": 2227,
      "慕う": 2228,
      "振りまく": 2229,
      "溜める": 2230,
      "うかべる": 2231,
      "かわいらしい": 2232,
      "見向く": 2233,
      "備わる": 2234,
      "見いだす": 2235,
      "追い越す": 2236,
      "抱き締める": 2237,
      "横たえる": 2238,
      "もぐる": 2239,
      "交える": 2240,
      "用立てる": 2241,
      "動ずる": 2242,
      "し終える": 2243,
      "遮る": 2244,
      "にらみつける": 2245,
      "引き止める": 2246,
      "浴びせる": 2247,
      "歩き去る": 2248,
      "跳び上がる": 2249,
      "突き落とす": 2250,
      "すくめる": 2251,
      "挟む": 2252,
      "畳む": 2253,
      "買わす": 2254,
      "しかめる": 2255,
      "読み返す": 2256,
      "投げ捨てる": 2257,
      "報いる": 2258,
      "引きつける": 2259,
      "威張る": 2260,
      "怒鳴りつける": 2261,
      "乗ずる": 2262,
      "明け渡す": 2263,
      "積み込む": 2264,
      "笑い飛ばす": 2265,
      "化する": 2266,
      "めげる": 2267,
      "跳ぶ": 2268,
      "km": 2269,
      "憎み合う": 2270,
      "なじむ": 2271,
      "うけたまわる": 2272,
      "老ける": 2273,
      "背く": 2274,
      "かかす": 2275,
      "つっこむ": 2276,
      "怒り狂う": 2277,
      "補う": 2278,
      "わびる": 2279,
      "投ずる": 2280,
      "ひっくり返る": 2281,
      "きらす": 2282,
      "はたす": 2283,
      "遠ざかる": 2284,
      "追いやる": 2285,
      "ゆがめる": 2286,
      "名乗る": 2287,
      "ひっかける": 2288,
      "思いきる": 2289,
      "博する": 2290,
      "駆け出す": 2291,
      "交わる": 2292,
      "つぶやく": 2293,
      "坐る": 2294,
      "放り出す": 2295,
      "こむ": 2296,
      "IBM": 2297,
      "蹴飛ばす": 2298,
      "しあげる": 2299,
      "合わす": 2300,
      "寝ぼける": 2301,
      "築き上げる": 2302,
      "免ずる": 2303,
      "いかれる": 2304,
      "あっけない": 2305,
      "38": 2306,
      "むしばむ": 2307,
      "出かかる": 2308,
      "結びつく": 2309,
      "あてがう": 2310,
      "おそれいる": 2311,
      "あおる": 2312,
      "のしかかる": 2313,
      "著しい": 2314,
      "動き始める": 2315,
      "干上がる": 2316,
      "跳ね上がる": 2317,
      "執り行う": 2318,
      "映し出す": 2319,
      "泊まれる": 2320,
      "座れる": 2321,
      "座り込む": 2322,
      "汚い": 2323,
      "4000": 2324,
      "とりやめる": 2325,
      "待ちくたびれる": 2326,
      "照りつける": 2327,
      "押しつける": 2328,
      "$": 2329,
      "想う": 2330,
      "酔いつぶれる": 2331,
      "折り入る": 2332,
      "埋め合わせる": 2333,
      "36": 2334,
      "o": 2335,
      "例える": 2336,
      "群がる": 2337,
      "隠し持つ": 2338,
      "語り継ぐ": 2339,
      "1992": 2340,
      "潔い": 2341,
      "むくむ": 2342,
      "切り上げる": 2343,
      "建て込む": 2344,
      "考えつく": 2345,
      "くらべる": 2346,
      "たく": 2347,
      "20万": 2348,
      "&": 2349,
      "縮む": 2350,
      "戸惑う": 2351,
      "どける": 2352,
      "かざす": 2353,
      "取り込む": 2354,
      "茂る": 2355,
      "さかのぼる": 2356,
      "懐かしい": 2357,
      "くもる": 2358,
      "600": 2359,
      "つづく": 2360,
      "すっぱい": 2361,
      "沸かす": 2362,
      "1600": 2363,
      "ずれる": 2364,
      "間にあう": 2365,
      "塩辛い": 2366,
      "やっつける": 2367,
      "焼け落ちる": 2368,
      "にる": 2369,
      "埋もれる": 2370,
      "停まる": 2371,
      "あずかる": 2372,
      "えらい": 2373,
      "捻る": 2374,
      "失せる": 2375,
      "TOM": 2376,
      "行ふ": 2377,
      "給ふ": 2378,
      "直せる": 2379,
      "ハマる": 2380,
      "めんどくさい": 2381,
      "解き明かす": 2382,
      "わめく": 2383,
      "跳ねる": 2384,
      "老け込む": 2385,
      "授かる": 2386,
      "浸かる": 2387,
      "巻き上げる": 2388,
      "46": 2389,
      "イケる": 2390,
      "引き下げる": 2391,
      "落ちつく": 2392,
      "排する": 2393,
      "ねる": 2394,
      "のこる": 2395,
      "へる": 2396,
      "暖まる": 2397,
      "就ける": 2398,
      "騒ぎ立てる": 2399,
      "破く": 2400,
      "たりる": 2401,
      "どかす": 2402,
      "悔しい": 2403,
      "さわぐ": 2404,
      "くっつける": 2405,
      "撒く": 2406,
      "かくれる": 2407,
      "擦り切れる": 2408,
      "空しい": 2409,
      "きびしい": 2410,
      "思い浮かぶ": 2411,
      "1991": 2412,
      "ながい": 2413,
      "j": 2414,
      "3456": 2415,
      "頼み込む": 2416,
      "釣れる": 2417,
      "辿る": 2418,
      "NHK": 2419,
      "巡る": 2420,
      "納める": 2421,
      "見あたる": 2422,
      "受けとる": 2423,
      "こじ開ける": 2424,
      "1977": 2425,
      "片付く": 2426,
      "くい止める": 2427,
      "1955": 2428,
      "1971": 2429,
      "4万": 2430,
      "33": 2431,
      "消せる": 2432,
      "1995": 2433,
      "1988": 2434,
      "棄てる": 2435,
      "明く": 2436,
      "怖れる": 2437,
      "あり": 2438,
      "点く": 2439,
      "舐める": 2440,
      "返せる": 2441,
      "Be": 2442,
      "浸す": 2443,
      "引き締める": 2444,
      "そそぐ": 2445,
      "呼び出せる": 2446,
      "立ち上げる": 2447,
      "はぐらかす": 2448,
      "駆り立てる": 2449,
      "適す": 2450,
      "およぶ": 2451,
      "Word": 2452,
      "ずらす": 2453,
      "軽々しい": 2454,
      "こぞる": 2455,
      "ゆう": 2456,
      "粗い": 2457,
      "払い戻す": 2458,
      "1500": 2459,
      "途切れる": 2460,
      "食い止める": 2461,
      "焼き上げる": 2462,
      "目す": 2463,
      "動きまわる": 2464,
      "屈む": 2465,
      "晴らす": 2466,
      "因む": 2467,
      "5814": 2468,
      "フル": 2469,
      "問いただす": 2470,
      "なじる": 2471,
      "81": 2472,
      "死に絶える": 2473,
      "焼け死ぬ": 2474,
      "指し示す": 2475,
      "仕込める": 2476,
      "現われる": 2477,
      "散らす": 2478,
      "こっぴどい": 2479,
      "打ち切る": 2480,
      "取り決める": 2481,
      "みまう": 2482,
      "くらむ": 2483,
      "つつむ": 2484,
      "捜し求める": 2485,
      "閉じこめる": 2486,
      "黙れる": 2487,
      "色づく": 2488,
      "しのぐ": 2489,
      "すすり泣く": 2490,
      "略す": 2491,
      "振れる": 2492,
      "おもえる": 2493,
      "かくまう": 2494,
      "寝転ぶ": 2495,
      "58": 2496,
      "鎮める": 2497,
      "だらしない": 2498,
      "保てる": 2499,
      "聞える": 2500,
      "はためく": 2501,
      "いそぐ": 2502,
      "積み重ねる": 2503,
      "入れ替える": 2504,
      "みなぎる": 2505,
      "立てかける": 2506,
      "混じる": 2507,
      "せきたてる": 2508,
      "みかける": 2509,
      "よぎる": 2510,
      "如く": 2511,
      "絶つ": 2512,
      "さそう": 2513,
      "ぬぐう": 2514,
      "1千万": 2515,
      "とりとめる": 2516,
      "喜ばす": 2517,
      "いとう": 2518,
      "たたずむ": 2519,
      "伍する": 2520,
      "すくむ": 2521,
      "引っ込める": 2522,
      "まぎれる": 2523,
      "きづく": 2524,
      "打ち勝てる": 2525,
      "買い込む": 2526,
      "またぐ": 2527,
      "際立つ": 2528,
      "握り締める": 2529,
      "信じ込む": 2530,
      "震え上がる": 2531,
      "気遣う": 2532,
      "笑いかける": 2533,
      "疑わしい": 2534,
      "突きつける": 2535,
      "かがみこむ": 2536,
      "満ちあふれる": 2537,
      "教え込む": 2538,
      "駆け下りる": 2539,
      "生ける": 2540,
      "自惚れる": 2541,
      "惚れ込む": 2542,
      "泣きわめく": 2543,
      "滑り降りる": 2544,
      "切り落とす": 2545,
      "付する": 2546,
      "すくない": 2547,
      "かがむ": 2548,
      "掃く": 2549,
      "悔いる": 2550,
      "言い切る": 2551,
      "釣り合う": 2552,
      "ぎこちない": 2553,
      "いらだつ": 2554,
      "見開く": 2555,
      "縛り付ける": 2556,
      "けしかける": 2557,
      "彫る": 2558,
      "似通う": 2559,
      "備え付ける": 2560,
      "断つ": 2561,
      "競い合う": 2562,
      "競う": 2563,
      "繰り上げる": 2564,
      "うなだれる": 2565,
      "そこねる": 2566,
      "いやす": 2567,
      "狩る": 2568,
      "ならべる": 2569,
      "話しあう": 2570,
      "食い違う": 2571,
      "消し止める": 2572,
      "落ちぶれる": 2573,
      "心地よい": 2574,
      "負わす": 2575,
      "とげる": 2576,
      "恨む": 2577,
      "にぎる": 2578,
      "世慣れる": 2579,
      "すする": 2580,
      "食いちぎる": 2581,
      "競いあう": 2582,
      "けがす": 2583,
      "生々しい": 2584,
      "かえりみる": 2585,
      "浸る": 2586,
      "揺する": 2587,
      "そむく": 2588,
      "めぐらす": 2589,
      "駆る": 2590,
      "濡らす": 2591,
      "つぐむ": 2592,
      "甘んずる": 2593,
      "死にかかる": 2594,
      "浮かす": 2595,
      "投げ入れる": 2596,
      "断ち切る": 2597,
      "晒す": 2598,
      "涙ぐむ": 2599,
      "拭う": 2600,
      "重んずる": 2601,
      "貼り付ける": 2602,
      "転ずる": 2603,
      "過る": 2604,
      "紛らす": 2605,
      "まさる": 2606,
      "しつける": 2607,
      "もろい": 2608,
      "飛び起きる": 2609,
      "罹る": 2610,
      "なづける": 2611,
      "とびつく": 2612,
      "書き換える": 2613,
      "かけこむ": 2614,
      "取り乱す": 2615,
      "しかける": 2616,
      "丸める": 2617,
      "救い出す": 2618,
      "抜け出せる": 2619,
      "せわしい": 2620,
      "とばす": 2621,
      "とりあげる": 2622,
      "まかす": 2623,
      "惜しい": 2624,
      "突く": 2625,
      "しらける": 2626,
      "滅入る": 2627,
      "溶け込む": 2628,
      "はじまる": 2629,
      "擦り減る": 2630,
      "25万": 2631,
      "にじむ": 2632,
      "3000万": 2633,
      "向き合う": 2634,
      "打ち寄せる": 2635,
      "蒔く": 2636,
      "耕す": 2637,
      "160": 2638,
      "雇える": 2639,
      "thank you": 2640,
      "下回る": 2641,
      "押さえつける": 2642,
      "降り注ぐ": 2643,
      "襲いかかる": 2644,
      "さしつかえる": 2645,
      "しばる": 2646,
      "羽織る": 2647,
      "超す": 2648,
      "張り合う": 2649,
      "吹きつける": 2650,
      "やすむ": 2651,
      "しおれる": 2652,
      "42": 2653,
      "祝する": 2654,
      "ちかい": 2655,
      "作り出す": 2656,
      "沈みかける": 2657,
      "ひかえる": 2658,
      "吐き出す": 2659,
      "いたむ": 2660,
      "ゆける": 2661,
      "取り下げる": 2662,
      "計り知れる": 2663,
      "あきる": 2664,
      "叩きのめす": 2665,
      "もてあそぶ": 2666,
      "枯れかける": 2667,
      "咎める": 2668,
      "早める": 2669,
      "XYZ": 2670,
      "なつく": 2671,
      "瞬く": 2672,
      "言い合う": 2673,
      "たまう": 2674,
      "静まりかえる": 2675,
      "慣らす": 2676,
      "溺れ死ぬ": 2677,
      "乗り越す": 2678,
      "しゃがむ": 2679,
      "1000万": 2680,
      "さばく": 2681,
      "P.S.": 2682,
      "かじかむ": 2683,
      "見まわす": 2684,
      "乗り合わせる": 2685,
      "ひねる": 2686,
      "たよる": 2687,
      "手伝える": 2688,
      "手がける": 2689,
      "1972": 2690,
      "走りまわる": 2691,
      "102": 2692,
      "すり減る": 2693,
      "はける": 2694,
      "引き離す": 2695,
      "あったかい": 2696,
      "高ぶる": 2697,
      "くだす": 2698,
      "t": 2699,
      "うかぶ": 2700,
      "はなせる": 2701,
      "105": 2702,
      "もとづく": 2703,
      "踏み込む": 2704,
      "長引く": 2705,
      "のびる": 2706,
      "塗り替える": 2707,
      "急く": 2708,
      "凍える": 2709,
      "吹き荒れる": 2710,
      "うなる": 2711,
      "無し": 2712,
      "くぼむ": 2713,
      "cfit": 2714,
      "起こせる": 2715,
      "もうかる": 2716,
      "7千": 2717,
      "支払える": 2718,
      "すう": 2719,
      "為す": 2720,
      "聞き逃す": 2721,
      "111": 2722,
      "苦い": 2723,
      "酷い": 2724,
      "願い出る": 2725,
      "1603": 2726,
      "登れる": 2727,
      "荒れ果てる": 2728,
      "29": 2729,
      "大人びる": 2730,
      "刻みつける": 2731,
      "崩れ落ちる": 2732,
      "たどりつく": 2733,
      "1976": 2734,
      "41": 2735,
      "JR": 2736,
      "存じ上げる": 2737,
      "1994": 2738,
      "dca": 2739,
      "撮れる": 2740,
      "取り仕切る": 2741,
      "描ける": 2742,
      "002": 2743,
      "湿気る": 2744,
      "適う": 2745,
      "割り切れる": 2746,
      "貸せる": 2747,
      "掛け直す": 2748,
      "あさる": 2749,
      "VISAカード": 2750,
      "USSR": 2751,
      "USA": 2752,
      "JAL": 2753,
      "u": 2754,
      "以つ": 2755,
      "怯える": 2756,
      "User": 2757,
      "煮込む": 2758,
      "。": 2759,
      "う~ん": 2760,
      "ミスる": 2761,
      "ONLY YOU": 2762,
      "悔む": 2763,
      "引き立てる": 2764,
      "熟れる": 2765,
      "呟く": 2766,
      "生まれ変わる": 2767,
      "手軽い": 2768,
      "繋ぐ": 2769,
      "凹む": 2770,
      "捉える": 2771,
      "請う": 2772,
      "仕向ける": 2773,
      "忘れかける": 2774,
      "FAX": 2775,
      "さりげない": 2776,
      "あかい": 2777,
      "尽かす": 2778,
      "紛れる": 2779,
      "さする": 2780,
      "ぬるい": 2781,
      "満つ": 2782,
      "49": 2783,
      "はがす": 2784,
      "言い返す": 2785,
      "ぶら下がる": 2786,
      "55": 2787,
      "つねる": 2788,
      "取り直す": 2789,
      "滑り落ちる": 2790,
      "脱げる": 2791,
      "叶える": 2792,
      "やらす": 2793,
      "とっつく": 2794,
      "釣り上げる": 2795,
      "しかりつける": 2796,
      "とどく": 2797,
      "充てる": 2798,
      "推し進める": 2799,
      "85": 2800,
      "立ち直れる": 2801,
      "つりあう": 2802,
      "落着く": 2803,
      "X線写真": 2804,
      "日暮れる": 2805,
      "4.5": 2806,
      "際する": 2807,
      "書き入れる": 2808,
      "001": 2809,
      "1964": 2810,
      "にぎわう": 2811,
      "弱める": 2812,
      "追い付く": 2813,
      "見出せる": 2814,
      "吸える": 2815,
      "1974": 2816,
      "差し迫る": 2817,
      "360": 2818,
      "植わる": 2819,
      "儲かる": 2820,
      "相応しい": 2821,
      "持ち込める": 2822,
      "頼める": 2823,
      "綴る": 2824,
      "AB": 2825,
      "立てこもる": 2826,
      "言い付かる": 2827,
      "潤す": 2828,
      "踊れる": 2829,
      "寝足りる": 2830,
      "拗ねる": 2831,
      "潰す": 2832,
      "かぎ回る": 2833,
      "かき消す": 2834,
      "据わる": 2835,
      "to": 2836,
      "打ち砕く": 2837,
      "そえる": 2838,
      "揚がる": 2839,
      "煮え立つ": 2840,
      "ダブる": 2841,
      "挟まる": 2842,
      "まとわりつく": 2843,
      "ぼかす": 2844,
      "2006": 2845,
      "ほこる": 2846,
      "深まる": 2847,
      "貶める": 2848,
      "すっぽ抜ける": 2849,
      "繰り広げる": 2850,
      "侮る": 2851,
      "手間取る": 2852,
      "唸る": 2853,
      "禿げる": 2854,
      "HIT": 2855,
      "とび出す": 2856,
      "撫でる": 2857,
      "ID": 2858,
      "ほっつき歩く": 2859,
      "振り回す": 2860,
      "強まる": 2861,
      "養える": 2862,
      "揺られる": 2863,
      "キレる": 2864,
      "持ち上がる": 2865,
      "干る": 2866,
      "噛み切る": 2867,
      "割り振る": 2868,
      "率いる": 2869,
      "担う": 2870,
      "大人しい": 2871,
      "48": 2872,
      "愚痴る": 2873,
      "懲りる": 2874,
      "殴り倒す": 2875,
      "遅らせる": 2876,
      "狭まる": 2877,
      "易い": 2878,
      "晴れ上がる": 2879,
      "吹き倒す": 2880,
      "まぜる": 2881,
      "立ちすくむ": 2882,
      "握りしめる": 2883,
      "着飾る": 2884,
      "せまる": 2885,
      "更ける": 2886,
      "織る": 2887,
      "舞う": 2888,
      "くくる": 2889,
      "すがりつく": 2890,
      "あざける": 2891,
      "温まる": 2892,
      "飲み歩く": 2893,
      "とかす": 2894,
      "呪う": 2895,
      "読みとる": 2896,
      "書きつける": 2897,
      "おちつく": 2898,
      "通える": 2899,
      "問いかける": 2900,
      "わるい": 2901,
      "持ちこたえる": 2902,
      "振るう": 2903,
      "込み上げる": 2904,
      "ぐらつく": 2905,
      "ひきだす": 2906,
      "そぐう": 2907,
      "KG": 2908,
      "うめく": 2909,
      "広める": 2910,
      "鈍い": 2911,
      "押しやる": 2912,
      "でかい": 2913,
      "旅慣れる": 2914,
      "考え込む": 2915,
      "運び込む": 2916,
      "いためる": 2917,
      "けす": 2918,
      "のれる": 2919,
      "ひらめく": 2920,
      "浮かれる": 2921,
      "勇ましい": 2922,
      "うつむく": 2923,
      "懸ける": 2924,
      "切り抜く": 2925,
      "逆立てる": 2926,
      "切り裂く": 2927,
      "寄り添う": 2928,
      "弱々しい": 2929,
      "図々しい": 2930,
      "巻き付ける": 2931,
      "結う": 2932,
      "黙り込む": 2933,
      "背ける": 2934,
      "つるす": 2935,
      "仕立て直す": 2936,
      "引き寄せる": 2937,
      "もぐ": 2938,
      "よだつ": 2939,
      "揚げる": 2940,
      "泣きじゃくる": 2941,
      "気難しい": 2942,
      "持て余す": 2943,
      "取りつく": 2944,
      "かぶせる": 2945,
      "かき回す": 2946,
      "たいらげる": 2947,
      "あえぐ": 2948,
      "つきとめる": 2949,
      "飲みほす": 2950,
      "拾い集める": 2951,
      "つむ": 2952,
      "わらう": 2953,
      "さげる": 2954,
      "溢れ出る": 2955,
      "かき立てる": 2956,
      "みのる": 2957,
      "よそよそしい": 2958,
      "通り越す": 2959,
      "逸する": 2960,
      "引っ込む": 2961,
      "速める": 2962,
      "はしゃぐ": 2963,
      "まもる": 2964,
      "走り出る": 2965,
      "ずうずうしい": 2966,
      "つけ加える": 2967,
      "奪い合う": 2968,
      "もとめる": 2969,
      "縛りつける": 2970,
      "ばらす": 2971,
      "沈める": 2972,
      "聞き漏らす": 2973,
      "なすりつける": 2974,
      "もめる": 2975,
      "出し抜く": 2976,
      "かわかす": 2977,
      "生き延びる": 2978,
      "論じ合う": 2979,
      "1989": 2980,
      "暴く": 2981,
      "這う": 2982,
      "だつ": 2983,
      "つむる": 2984,
      "押しあてる": 2985,
      "飛び回る": 2986,
      "たたる": 2987,
      "引きこもる": 2988,
      "おどす": 2989,
      "あがめる": 2990,
      "たしなめる": 2991,
      "駆け寄る": 2992,
      "踏みにじる": 2993,
      "腰かける": 2994,
      "のろう": 2995,
      "ほれこむ": 2996,
      "思い直す": 2997,
      "形作る": 2998,
      "あぶる": 2999,
      "訪ね歩く": 3000,
      "乗り違える": 3001,
      "食らわせる": 3002,
      "たたきつける": 3003,
      "こしらえる": 3004,
      "垂れる": 3005,
      "思わしい": 3006,
      "ふやす": 3007,
      "憎める": 3008,
      "しかたない": 3009,
      "優る": 3010,
      "浮かび上がる": 3011,
      "なおる": 3012,
      "仕込む": 3013,
      "渋る": 3014,
      "かさむ": 3015,
      "吹かす": 3016,
      "寝転がる": 3017,
      "立ちふさがる": 3018,
      "やりとげる": 3019,
      "くらます": 3020,
      "取り違える": 3021,
      "撃ち抜く": 3022,
      "担ぐ": 3023,
      "居残る": 3024,
      "打ち付ける": 3025,
      "よじ登る": 3026,
      "引き延ばす": 3027,
      "育て上げる": 3028,
      "突き刺す": 3029,
      "転がり落ちる": 3030,
      "考えだす": 3031,
      "もくろむ": 3032,
      "ほめたたえる": 3033,
      "縛り上げる": 3034,
      "もぎ取る": 3035,
      "投げ返す": 3036,
      "ふかす": 3037,
      "立ち上がれる": 3038,
      "請け負う": 3039,
      "ぼける": 3040,
      "立ちよる": 3041,
      "すくう": 3042,
      "座りこむ": 3043,
      "FBI": 3044,
      "418": 3045,
      "ねむる": 3046,
      "1921": 3047,
      "幅広い": 3048,
      "即する": 3049,
      "揺るぐ": 3050,
      "もたげる": 3051,
      "転がり込む": 3052,
      "打ちひしぐ": 3053,
      "砕く": 3054,
      "流れ出る": 3055,
      "乗り過ごす": 3056,
      "光り輝く": 3057,
      "浮き上がる": 3058,
      "防げる": 3059,
      "たたきのめす": 3060,
      "なだれ込む": 3061,
      "引っかく": 3062,
      "濁る": 3063,
      "2億": 3064,
      "かけ離れる": 3065,
      "100億": 3066,
      "52": 3067,
      "47": 3068,
      "4億": 3069,
      "3億": 3070,
      "読み直す": 3071,
      "住み着く": 3072,
      "たくましい": 3073,
      "99": 3074,
      "紛れ込む": 3075,
      "あるく": 3076,
      "生い茂る": 3077,
      "is": 3078,
      "見え透く": 3079,
      "ほどよい": 3080,
      "ぬける": 3081,
      "365": 3082,
      "3千": 3083,
      "取りはずす": 3084,
      "解き放つ": 3085,
      "聞き取る": 3086,
      "ともる": 3087,
      "没する": 3088,
      "遠のく": 3089,
      "つくれる": 3090,
      "たたかう": 3091,
      "かじりつく": 3092,
      "流れ込む": 3093,
      "架ける": 3094,
      "すっぽかす": 3095,
      "1.5": 3096,
      "引き立つ": 3097,
      "きりつめる": 3098,
      "連れ戻す": 3099,
      "やり直せる": 3100,
      "哀れむ": 3101,
      "溜まる": 3102,
      "たすける": 3103,
      "ふんぞる": 3104,
      "めいる": 3105,
      "裁く": 3106,
      "出れる": 3107,
      "吹き返す": 3108,
      "脱ぎ捨てる": 3109,
      "見越す": 3110,
      "くたびれる": 3111,
      "0.7": 3112,
      "はさまる": 3113,
      "ひびく": 3114,
      "振り切る": 3115,
      "ひんする": 3116,
      "信じる": 3117,
      "張り出す": 3118,
      "淋しい": 3119,
      "聞き出す": 3120,
      "成り下がる": 3121,
      "わたす": 3122,
      "抜かす": 3123,
      "引っ掛かる": 3124,
      "ほうり出す": 3125,
      "落ち合う": 3126,
      "とどこおる": 3127,
      "ひなびる": 3128,
      "繕う": 3129,
      "紡ぐ": 3130,
      "1985": 3131,
      "1968": 3132,
      "1962": 3133,
      "1940": 3134,
      "すり切れる": 3135,
      "噴き出す": 3136,
      "213": 3137,
      "映す": 3138,
      "かたい": 3139,
      "I": 3140,
      "噛み合う": 3141,
      "冷え込む": 3142,
      "思い詰める": 3143,
      "伸ばせる": 3144,
      "こわれかかる": 3145,
      "しのぶ": 3146,
      "取り消せる": 3147,
      "追い詰める": 3148,
      "争える": 3149,
      "155": 3150,
      "どす黒い": 3151,
      "仕掛ける": 3152,
      "照らし合わせる": 3153,
      "跳べる": 3154,
      "刈り取る": 3155,
      "拘る": 3156,
      "きらめく": 3157,
      "絡む": 3158,
      "明け暮れる": 3159,
      "醜い": 3160,
      "あつまる": 3161,
      "PTA": 3162,
      "潜る": 3163,
      "容れる": 3164,
      "くさる": 3165,
      "取り戻せる": 3166,
      "憎みあう": 3167,
      "少い": 3168,
      "燃え尽きる": 3169,
      "1860": 3170,
      "くべる": 3171,
      "1910": 3172,
      "はずむ": 3173,
      "まねる": 3174,
      "ばらまく": 3175,
      "1853": 3176,
      "煮えくる": 3177,
      "うしなう": 3178,
      "デブる": 3179,
      "DOC": 3180,
      "高価い": 3181,
      "架かる": 3182,
      "ほど遠い": 3183,
      "しのげる": 3184,
      "掴まえる": 3185,
      "宿る": 3186,
      "まみれる": 3187,
      "断れる": 3188,
      "使い分ける": 3189,
      "get": 3190,
      "連ねる": 3191,
      "焼きあがる": 3192,
      "LILY": 3193,
      "SF小説": 3194,
      "捕える": 3195,
      "呑む": 3196,
      "取り外す": 3197,
      "久い": 3198,
      "思い描く": 3199,
      "ちう": 3200,
      "くたばる": 3201,
      "WHO": 3202,
      "PKO": 3203,
      "CO2": 3204,
      "偏る": 3205,
      "だまし取る": 3206,
      "うざい": 3207,
      "盛る": 3208,
      "不味い": 3209,
      "腫れる": 3210,
      "くぐる": 3211,
      "ぶん殴る": 3212,
      "揉む": 3213,
      "パクる": 3214,
      "びびる": 3215,
      "書きとめる": 3216,
      "駐まる": 3217,
      "思ふ": 3218,
      "1497": 3219,
      "絞め殺す": 3220,
      "振り絞る": 3221,
      "突っ立つ": 3222,
      "解す": 3223,
      "BB": 3224,
      "へこむ": 3225,
      "揺らぐ": 3226,
      "る": 3227,
      "恋う": 3228,
      "期する": 3229,
      "2013": 3230,
      "吹ける": 3231,
      "R": 3232,
      "ツク": 3233,
      "召し上がれる": 3234,
      "舞い降りる": 3235,
      "甲斐甲斐しい": 3236,
      "萌える": 3237,
      "すっ転ぶ": 3238,
      "逝く": 3239,
      "追い返す": 3240,
      "67": 3241,
      "貯まる": 3242,
      "延ばせる": 3243,
      "受取る": 3244,
      "空かす": 3245,
      "ころす": 3246,
      "祭り上げる": 3247,
      "かばう": 3248,
      "脅える": 3249,
      "7万": 3250,
      "まがる": 3251,
      "聞きとれる": 3252,
      "呼び寄せる": 3253,
      "制する": 3254,
      "研ぐ": 3255,
      "であう": 3256,
      "10000": 3257,
      "くつがえす": 3258,
      "1930": 3259,
      "寝付ける": 3260,
      "改まる": 3261,
      "閉め出す": 3262,
      "50億": 3263,
      "のろい": 3264,
      "命ず": 3265,
      "170": 3266,
      "とりあう": 3267,
      "低し": 3268,
      "沸き立つ": 3269,
      "封じ込む": 3270,
      "どる": 3271,
      "待ち合わせる": 3272,
      "徹する": 3273,
      "もちあわせる": 3274,
      "1948": 3275,
      "37": 3276,
      "きづかう": 3277,
      "讃える": 3278,
      "絞める": 3279,
      "立て込む": 3280,
      "やせこける": 3281,
      "ささる": 3282,
      "くり返す": 3283,
      "伴る": 3284,
      "頑張れる": 3285,
      "降り止む": 3286,
      "1900": 3287,
      "かんずる": 3288,
      "がける": 3289,
      "1963": 3290,
      "焼き払う": 3291,
      "1918": 3292,
      "ds": 3293,
      "し終わる": 3294,
      "煩う": 3295,
      "こく": 3296,
      "DTA": 3297,
      "61": 3298,
      "浮ぶ": 3299,
      "8.8": 3300,
      "狭める": 3301,
      "馬鹿馬鹿しい": 3302,
      "拭える": 3303,
      "譲り合う": 3304,
      "2003": 3305
    }
  },
  "lemma_min_freq": 5,
  "max_lemma_vocab": 10000,
  "frozen": true
}